mieszkaivision/__init__.py
mieszkaivision/compare_pictures.py
mieszkaivision/picture_classifier_umap.py
mieszkaivision-0.1.3.dist-info/METADATA
mieszkaivision-0.1.3.dist-info/WHEEL
mieszkaivision-0.1.3.dist-info/top_level.txt
mieszkaivision-0.1.3.dist-info/zip-safe
mieszkaivision-0.1.3.dist-info/RECORD
