Metadata-Version: 2.1
Name: mieszkaivision
Version: 0.1.3
Summary: Tools to analyze pictures of apartments
Home-page: https://gitlab.com/stasulam/mieszkai-api/tree/v0.1/mieszkaivision
Author: Lukasz Bala
Author-email: UNKNOWN
License: MIT
Platform: UNKNOWN
Requires-Dist: pip (==18.1)
Requires-Dist: numpy (==1.15.4)
Requires-Dist: pandas (==0.23.4)
Requires-Dist: pillow (==5.3.0)
Requires-Dist: opencv-python (==3.4.4.19)
Requires-Dist: keras (==2.2.4)
Requires-Dist: tensorflow (==1.12.0)
Requires-Dist: hdbscan (==0.8.18)
